panoseti_grpc/__init__.py
panoseti_grpc/daq_data/__init__.py
panoseti_grpc/daq_data/cli.py
panoseti_grpc/daq_data/client.py
panoseti_grpc/daq_data/data_sources.py
panoseti_grpc/daq_data/hp_io_manager.py
panoseti_grpc/daq_data/managers.py
panoseti_grpc/daq_data/plot.py
panoseti_grpc/daq_data/resources.py
panoseti_grpc/daq_data/server.py
panoseti_grpc/daq_data/simulate.py
panoseti_grpc/daq_data/state.py
panoseti_grpc/daq_data/testing.py
panoseti_grpc/daq_data/config/daq_config_grpc_simulate.json
panoseti_grpc/daq_data/config/daq_data_server_config.json
panoseti_grpc/daq_data/config/hp_io_config_lick.json
panoseti_grpc/daq_data/config/hp_io_config_palomar.json
panoseti_grpc/daq_data/config/hp_io_config_simulate.json
panoseti_grpc/daq_data/config/network_config_grpc_simulate.json
panoseti_grpc/daq_data/simulated_data_dir/obs_Lick.start_2024-07-25T04:34:06Z.runtype_sci-data.pffd/daq_config.json
panoseti_grpc/daq_data/simulated_data_dir/obs_Lick.start_2024-07-25T04:34:06Z.runtype_sci-data.pffd/data_config.json
panoseti_grpc/daq_data/simulated_data_dir/obs_Lick.start_2024-07-25T04:34:06Z.runtype_sci-data.pffd/obs_config.json
panoseti_grpc/daq_data/simulated_data_dir/obs_Lick.start_2024-07-25T04:34:06Z.runtype_sci-data.pffd/quabo_ph_baseline.json
panoseti_grpc/daq_data/simulated_data_dir/obs_Lick.start_2024-07-25T04:34:06Z.runtype_sci-data.pffd/quabo_uids.json
panoseti_grpc/daq_data/simulated_data_dir/obs_Lick.start_2024-07-25T04:34:06Z.runtype_sci-data.pffd/recording_ended
panoseti_grpc/daq_data/simulated_data_dir/obs_Lick.start_2024-07-25T04:34:06Z.runtype_sci-data.pffd/start_2024-07-25T04_34_46Z.dp_img16.bpp_2.module_1.seqno_0.debug_TRUNCATED.pff
panoseti_grpc/daq_data/simulated_data_dir/obs_Lick.start_2024-07-25T04:34:06Z.runtype_sci-data.pffd/start_2024-07-25T04_34_46Z.dp_ph256.bpp_2.module_1.seqno_0.debug_TRUNCATED.pff
panoseti_grpc-0.2.14.dist-info/licenses/LICENSE
panoseti_grpc-0.2.14.dist-info/METADATA
panoseti_grpc-0.2.14.dist-info/WHEEL
panoseti_grpc-0.2.14.dist-info/top_level.txt
panoseti_grpc-0.2.14.dist-info/RECORD
