Metadata-Version: 2.4
Name: panoseti-grpc
Version: 0.2.14
Summary: gRPC for the PANOSETI project.
Author: Nicolas Rault-Wang, Ben Godfrey
Project-URL: Homepage, https://github.com/panoseti/panoseti_grpc
Project-URL: Documentation, https://github.com/panoseti/panoseti_grpc/blob/main/README.md
Project-URL: Repository, https://github.com/panoseti/panoseti_grpc
Project-URL: Issues, https://github.com/panoseti/panoseti_grpc/issues
Keywords: panoseti,gRPC,observatory,data-acquisition,astronomy,real-time
Classifier: Programming Language :: Python :: 3
Classifier: Operating System :: Unix
Classifier: Intended Audience :: Science/Research
Classifier: Topic :: Scientific/Engineering :: Astronomy
Classifier: Framework :: AsyncIO
Requires-Python: >=3.9
License-File: LICENSE
Requires-Dist: grpcio==1.70.0
Requires-Dist: grpcio-tools==1.70.0
Requires-Dist: grpcio-reflection==1.70.0
Requires-Dist: protobuf<6.0.0,>=5.26.1
Requires-Dist: coverage>=7.10.7
Requires-Dist: cython
Requires-Dist: wheel
Requires-Dist: rich
Requires-Dist: redis>=7
Requires-Dist: snakeviz
Requires-Dist: json5
Requires-Dist: pyserial
Requires-Dist: pyubx2
Requires-Dist: seaborn
Requires-Dist: matplotlib
Requires-Dist: pandas
Requires-Dist: numpy
Requires-Dist: psutil
Requires-Dist: watchfiles
Requires-Dist: aiofiles
Requires-Dist: pygnssutils
Requires-Dist: pydantic
Requires-Dist: tomli
Provides-Extra: dev
Requires-Dist: pytest; extra == "dev"
Requires-Dist: black; extra == "dev"
Requires-Dist: flake8; extra == "dev"
Requires-Dist: ipython; extra == "dev"
Provides-Extra: docs
Requires-Dist: sphinx; extra == "docs"
Requires-Dist: myst-parser; extra == "docs"
Requires-Dist: sphinx-autodoc-typehints; extra == "docs"
Dynamic: license-file
